{"Agricultores" : [{"coda":1001,"nomea":"Ana Maria Machado","cidadea":"Mogi das Cruzes"}, {"coda":1002,"nomea":"José de Alencar","cidadea":"Mogi das Cruzes"}, {"coda":1003,"nomea":"Manuel Bandeira","cidadea":"Mogi das Cruzes"}, {"coda":1004,"nomea":"Machado de Assis","cidadea":"Atibaia"}, {"coda":1005,"nomea":"Oswald de Andrade","cidadea":"Atibaia"}, {"coda":1006,"nomea":"Lima Barreto","cidadea":"São Paulo"}, {"coda":1007,"nomea":"Cecília Meireles","cidadea":"São Paulo"}, {"coda":1008,"nomea":"Castro Alves","cidadea":"Campinas"}, {"coda":1009,"nomea":"Monteiro Lobato","cidadea":"Taubaté"}], "Produtos" : [{"codp":2001,"nomep":"tomate","precoquilo":4.98}, {"codp":2002,"nomep":"batata","precoquilo":0.98}, {"codp":2003,"nomep":"cebola","precoquilo":2.98}, {"codp":2004,"nomep":"cenoura","precoquilo":1.98}, {"codp":2005,"nomep":"chuchu","precoquilo":2.49}, {"codp":2006,"nomep":"mandioca","precoquilo":1.98}, {"codp":2007,"nomep":"couve-flor","precoquilo":3.90}, {"codp":2008,"nomep":"quiabo","precoquilo":8.98}, {"codp":2009,"nomep":"pimentão","precoquilo":3.98}, {"codp":2010,"nomep":"repolho","precoquilo":1.49}, {"codp":2011,"nomep":"beterraba","precoquilo":2.49}, {"codp":2012,"nomep":"alface","precoquilo":2.98}, {"codp":2013,"nomep":"tomate cereja","precoquilo":5.98}], "Restaurantes" : [{"codr":3001,"nomer":"Brasileirinho","cidader":"São Paulo"}, {"codr":3002,"nomer":"Sabor de Minas","cidader":"Santo André"}, {"codr":3003,"nomer":"Bom Gosto","cidader":"Atibaia"}, {"codr":3004,"nomer":"Panela de Ouro","cidader":"São Paulo"}, {"codr":3005,"nomer":"RU-USP","cidader":"São Paulo"}, {"codr":3006,"nomer":"Bom de Garfo","cidader":"Osasco"}, {"codr":3007,"nomer":"Sabores do Interior","cidader":"Osasco"}, {"codr":3008,"nomer":"Brasil a Gosto","cidader":"São Caetano"}, {"codr":3009,"nomer":"Prato-Cheio","cidader":"Diadema"}, {"codr":3010,"nomer":"A Todo Sabor","cidader":"Mogi das Cruzes"}], "Entregas" : [{"coda":1001,"agricultor":{"coda":1001,"nomea":"Ana Maria Machado","cidadea":"Mogi das Cruzes"},"restaurante":{"codr":3010,"nomer":"A Todo Sabor","cidader":"Mogi das Cruzes"},"produto":{"codp":2005,"nomep":"chuchu","precoquilo":2.49}}, {"coda":1004,"agricultor":{"coda":1004,"nomea":"Machado de Assis","cidadea":"Atibaia"},"restaurante":{"codr":3005,"nomer":"RU-USP","cidader":"São Paulo"},"produto":{"codp":2002,"nomep":"batata","precoquilo":0.98}}, {"coda":1006,"agricultor":{"coda":1006,"nomea":"Lima Barreto","cidadea":"São Paulo"},"restaurante":{"codr":3002,"nomer":"Sabor de Minas","cidader":"Santo André"},"produto":{"codp":2011,"nomep":"beterraba","precoquilo":2.49}}, {"coda":1003,"agricultor":{"coda":1003,"nomea":"Manuel Bandeira","cidadea":"Mogi das Cruzes"},"restaurante":{"codr":3009,"nomer":"Prato-Cheio","cidader":"Diadema"},"produto":{"codp":2003,"nomep":"cebola","precoquilo":2.98}}, {"coda":1004,"agricultor":{"coda":1004,"nomea":"Machado de Assis","cidadea":"Atibaia"},"restaurante":{"codr":3008,"nomer":"Brasil a Gosto","cidader":"São Caetano"},"produto":{"codp":2008,"nomep":"quiabo","precoquilo":8.98}}, {"coda":1007,"agricultor":{"coda":1007,"nomea":"Cecília Meireles","cidadea":"São Paulo"},"restaurante":{"codr":3003,"nomer":"Bom Gosto","cidader":"Atibaia"},"produto":{"codp":2008,"nomep":"quiabo","precoquilo":8.98}}, {"coda":1005,"agricultor":{"coda":1005,"nomea":"Oswald de Andrade","cidadea":"Atibaia"},"restaurante":{"codr":3002,"nomer":"Sabor de Minas","cidader":"Santo André"},"produto":{"codp":2002,"nomep":"batata","precoquilo":0.98}}, {"coda":1005,"agricultor":{"coda":1005,"nomea":"Oswald de Andrade","cidadea":"Atibaia"},"restaurante":{"codr":3002,"nomer":"Sabor de Minas","cidader":"Santo André"},"produto":{"codp":2001,"nomep":"tomate","precoquilo":4.98}}, {"coda":1002,"agricultor":{"coda":1002,"nomea":"José de Alencar","cidadea":"Mogi das Cruzes"},"restaurante":{"codr":3010,"nomer":"A Todo Sabor","cidader":"Mogi das Cruzes"},"produto":{"codp":2002,"nomep":"batata","precoquilo":0.98}}, {"coda":1002,"agricultor":{"coda":1002,"nomea":"José de Alencar","cidadea":"Mogi das Cruzes"},"restaurante":{"codr":3006,"nomer":"Bom de Garfo","cidader":"Osasco"},"produto":{"codp":2007,"nomep":"couve-flor","precoquilo":3.90}}, {"coda":1004,"agricultor":{"coda":1004,"nomea":"Machado de Assis","cidadea":"Atibaia"},"restaurante":{"codr":3006,"nomer":"Bom de Garfo","cidader":"Osasco"},"produto":{"codp":2010,"nomep":"repolho","precoquilo":1.49}}, {"coda":1007,"agricultor":{"coda":1007,"nomea":"Cecília Meireles","cidadea":"São Paulo"},"restaurante":{"codr":3004,"nomer":"Panela de Ouro","cidader":"São Paulo"},"produto":{"codp":2003,"nomep":"cebola","precoquilo":2.98}}, {"coda":1002,"agricultor":{"coda":1002,"nomea":"José de Alencar","cidadea":"Mogi das Cruzes"},"restaurante":{"codr":3002,"nomer":"Sabor de Minas","cidader":"Santo André"},"produto":{"codp":2005,"nomep":"chuchu","precoquilo":2.49}}, {"coda":1002,"agricultor":{"coda":1002,"nomea":"José de Alencar","cidadea":"Mogi das Cruzes"},"restaurante":{"codr":3004,"nomer":"Panela de Ouro","cidader":"São Paulo"},"produto":{"codp":2003,"nomep":"cebola","precoquilo":2.98}}, {"coda":1004,"agricultor":{"coda":1004,"nomea":"Machado de Assis","cidadea":"Atibaia"},"restaurante":{"codr":3002,"nomer":"Sabor de Minas","cidader":"Santo André"},"produto":{"codp":2005,"nomep":"chuchu","precoquilo":2.49}}, {"coda":1005,"agricultor":{"coda":1005,"nomea":"Oswald de Andrade","cidadea":"Atibaia"},"restaurante":{"codr":3002,"nomer":"Sabor de Minas","cidader":"Santo André"},"produto":{"codp":2011,"nomep":"beterraba","precoquilo":2.49}}, {"coda":1001,"agricultor":{"coda":1001,"nomea":"Ana Maria Machado","cidadea":"Mogi das Cruzes"},"restaurante":{"codr":3002,"nomer":"Sabor de Minas","cidader":"Santo André"},"produto":{"codp":2003,"nomep":"cebola","precoquilo":2.98}}, {"coda":1003,"agricultor":{"coda":1003,"nomea":"Manuel Bandeira","cidadea":"Mogi das Cruzes"},"restaurante":{"codr":3010,"nomer":"A Todo Sabor","cidader":"Mogi das Cruzes"},"produto":{"codp":2002,"nomep":"batata","precoquilo":0.98}}, {"coda":1003,"agricultor":{"coda":1003,"nomea":"Manuel Bandeira","cidadea":"Mogi das Cruzes"},"restaurante":{"codr":3006,"nomer":"Bom de Garfo","cidader":"Osasco"},"produto":{"codp":2012,"nomep":"alface","precoquilo":2.98}}, {"coda":1007,"agricultor":{"coda":1007,"nomea":"Cecília Meireles","cidadea":"São Paulo"},"restaurante":{"codr":3006,"nomer":"Bom de Garfo","cidader":"Osasco"},"produto":{"codp":2007,"nomep":"couve-flor","precoquilo":3.90}}, {"coda":1006,"agricultor":{"coda":1006,"nomea":"Lima Barreto","cidadea":"São Paulo"},"restaurante":{"codr":3001,"nomer":"Brasileirinho","cidader":"São Paulo"},"produto":{"codp":2003,"nomep":"cebola","precoquilo":2.98}}, {"coda":1002,"agricultor":{"coda":1002,"nomea":"José de Alencar","cidadea":"Mogi das Cruzes"},"restaurante":{"codr":3003,"nomer":"Bom Gosto","cidader":"Atibaia"},"produto":{"codp":2003,"nomep":"cebola","precoquilo":2.98}}, {"coda":1001,"agricultor":{"coda":1001,"nomea":"Ana Maria Machado","cidadea":"Mogi das Cruzes"},"restaurante":{"codr":3005,"nomer":"RU-USP","cidader":"São Paulo"},"produto":{"codp":2003,"nomep":"cebola","precoquilo":2.98}}, {"coda":1007,"agricultor":{"coda":1007,"nomea":"Cecília Meireles","cidadea":"São Paulo"},"restaurante":{"codr":3006,"nomer":"Bom de Garfo","cidader":"Osasco"},"produto":{"codp":2003,"nomep":"cebola","precoquilo":2.98}}, {"coda":1003,"agricultor":{"coda":1003,"nomea":"Manuel Bandeira","cidadea":"Mogi das Cruzes"},"restaurante":{"codr":3007,"nomer":"Sabores do Interior","cidader":"Osasco"},"produto":{"codp":2003,"nomep":"cebola","precoquilo":2.98}}, {"coda":1003,"agricultor":{"coda":1003,"nomea":"Manuel Bandeira","cidadea":"Mogi das Cruzes"},"restaurante":{"codr":3008,"nomer":"Brasil a Gosto","cidader":"São Caetano"},"produto":{"codp":2003,"nomep":"cebola","precoquilo":2.98}}, {"coda":1004,"agricultor":{"coda":1004,"nomea":"Machado de Assis","cidadea":"Atibaia"},"restaurante":{"codr":3010,"nomer":"A Todo Sabor","cidader":"Mogi das Cruzes"},"produto":{"codp":2003,"nomep":"cebola","precoquilo":2.98}}]}